gip/__init__.py
gip/bootstrap.py
gip/main.py
gip/mixture_modelling.py
gip/mutual_information.py
gip/process_normalise.py
gip/utils.py
gip_bio-0.1.0.dist-info/LICENCE
gip_bio-0.1.0.dist-info/METADATA
gip_bio-0.1.0.dist-info/WHEEL
gip_bio-0.1.0.dist-info/top_level.txt
gip_bio-0.1.0.dist-info/RECORD
