Metadata-Version: 2.1
Name: gip-bio
Version: 0.1.0
Summary: GIP -- Gaussian Interaction Profiler
Home-page: https://github.com/joerivstrien/gip-bio
Author: Joeri van Strien
Author-email: joerivanstrien@gmail.com
Project-URL: Bug Tracker, https://github.com/joerivstrien/gip-bio/issues
Classifier: Programming Language :: Python :: 3
Classifier: Operating System :: OS Independent
Requires-Python: >=3.7
License-File: LICENCE
Requires-Dist: numpy
Requires-Dist: pandas
Requires-Dist: scikit-learn
Requires-Dist: scipy
Requires-Dist: matplotlib
Requires-Dist: seaborn
Provides-Extra: test
Requires-Dist: pytest ; extra == 'test'
Requires-Dist: coverage ; extra == 'test'
Requires-Dist: pytest-cov ; extra == 'test'
